{"totalResults":3,"page":1,"totalPages":1,"perPage":24,"cursor":"AoMIQEo8Uz8GNjAwQWNhbnRoYWNlYWVTdGVuYW5kcml1bXZpbGxhcnJvZWxpaSxUYXhvbl82NDI3Mjc=","message":"If you would like to download and use the POWO data in a conciencious way, please use our official library pykew [https://github.com/RBGKew/pykew].","results":[{"accepted":true,"author":"Benth.","kingdom":"Plantae","family":"Fabaceae","name":"Arachis glabrata","rank":"Species","url":"/taxon/urn:lsid:ipni.org:names:474927-1","fqId":"urn:lsid:ipni.org:names:474927-1","images":[{"thumbnail":"//d2seqvvyy3b8p2.cloudfront.net/2dd97290170257c2f678acbcd024c785.jpg","fullsize":"//d2seqvvyy3b8p2.cloudfront.net/634820b97eeeb93c8544eb7ca587855a.jpg","caption":"A specimen from Kew's Herbarium"}]},{"accepted":true,"author":"J.R.I.Wood & Scotland","kingdom":"Plantae","family":"Convolvulaceae","name":"Ipomoea mucronatoproducta","rank":"Species","snippet":" <b>General</b>:  in association with Abildgardia ovata (Burm. f.) Kral, <em>Arachis</em> <em>glabrata</em>","url":"/taxon/urn:lsid:ipni.org:names:77148118-1","fqId":"urn:lsid:ipni.org:names:77148118-1"},{"accepted":true,"author":"J.R.I.Wood","kingdom":"Plantae","family":"Acanthaceae","name":"Stenandrium villarroelii","rank":"Species","snippet":" <b>General</b>:  ovata (Burm. f.) Kral, <em>Arachis</em> <em>glabrata</em> Benth., Elionurusmuticus","url":"/taxon/urn:lsid:ipni.org:names:77118658-1","fqId":"urn:lsid:ipni.org:names:77118658-1","images":[{"thumbnail":"//d2seqvvyy3b8p2.cloudfront.net/dd9fd0a3de1fe40dc759d532a9d3a96b.jpg","fullsize":"//d2seqvvyy3b8p2.cloudfront.net/4603a8496f9343ad0ad0f385de0a2544.jpg","caption":"A specimen from Kew's Herbarium"}]}]}