{"totalResults":4,"page":1,"totalPages":1,"perPage":24,"cursor":"AoMIQFZGfz42MDBMYXVyYWNlYWVDaW5uYW1vbXVtYnVybWFubmksVGF4b25fMjkzNzk3","message":"If you would like to download and use the POWO data in a conciencious way, please use our official library pykew [https://github.com/RBGKew/pykew].","results":[{"accepted":false,"author":"Nees ex Blume","kingdom":"Plantae","family":"Lauraceae","name":"Cinnamomum cassia","rank":"Species","synonymOf":{"accepted":true,"author":"(Nees & T.Nees) Blume","name":"Cinnamomum burmanni","url":"/taxon/urn:lsid:ipni.org:names:463328-1","fqId":"urn:lsid:ipni.org:names:463328-1"},"url":"/taxon/urn:lsid:ipni.org:names:463347-1","fqId":"urn:lsid:ipni.org:names:463347-1"},{"accepted":false,"author":"(L.) J.Presl","kingdom":"Plantae","family":"Lauraceae","name":"Cinnamomum cassia","rank":"Species","snippet":" <b>Common Name</b>: cassia","synonymOf":{"accepted":true,"author":"(L.) Kosterm.","name":"Neolitsea cassia","url":"/taxon/urn:lsid:ipni.org:names:466940-1","fqId":"urn:lsid:ipni.org:names:466940-1"},"url":"/taxon/urn:lsid:ipni.org:names:77109079-1","fqId":"urn:lsid:ipni.org:names:77109079-1"},{"accepted":true,"author":"(L.) Kosterm.","kingdom":"Plantae","family":"Lauraceae","name":"Neolitsea cassia","rank":"Species","snippet":" <b>Common Name</b>: dauul kurundu","url":"/taxon/urn:lsid:ipni.org:names:466940-1","fqId":"urn:lsid:ipni.org:names:466940-1","images":[{"thumbnail":"//d2seqvvyy3b8p2.cloudfront.net/b5249d4b48dff9a8618c85f6fcbb10a9.jpg","fullsize":"//d2seqvvyy3b8p2.cloudfront.net/8af12bea6e92bac8f0fa8bbd6509e8e3.jpg","caption":"Neolitsea cassia"},{"thumbnail":"//d2seqvvyy3b8p2.cloudfront.net/67902107934747d0863cce944583d117.jpg","fullsize":"//d2seqvvyy3b8p2.cloudfront.net/01a049c0a32236cd424760766eca2e30.jpg","caption":"Neolitsea cassia"},{"thumbnail":"//d2seqvvyy3b8p2.cloudfront.net/ff0825233ea3f13d630239c288c283b5.jpg","fullsize":"//d2seqvvyy3b8p2.cloudfront.net/c9b6ceb81f178fd95ba4b63d83c7731d.jpg","caption":"Neolitsea cassia"}]},{"accepted":true,"author":"(Nees & T.Nees) Blume","kingdom":"Plantae","family":"Lauraceae","name":"Cinnamomum burmanni","rank":"Species","snippet":" <b>Common Name</b>: karoa pateh","url":"/taxon/urn:lsid:ipni.org:names:463328-1","fqId":"urn:lsid:ipni.org:names:463328-1","images":[{"thumbnail":"//d2seqvvyy3b8p2.cloudfront.net/f9139648a223883abb38ee5c1e9c327e.jpg","fullsize":"//d2seqvvyy3b8p2.cloudfront.net/160063e8e5bdb3659c28263540d4b376.jpg","caption":"Cinnamomum burmanni"},{"thumbnail":"//d2seqvvyy3b8p2.cloudfront.net/75d99c979a53239ce555af672f233a21.jpg","fullsize":"//d2seqvvyy3b8p2.cloudfront.net/1642d886568b4f78f9cc4a2d28893d21.jpg","caption":"Cinnamomum burmanni"},{"thumbnail":"//d2seqvvyy3b8p2.cloudfront.net/a3067a10541ef3bf49689c739a39687a.jpg","fullsize":"//d2seqvvyy3b8p2.cloudfront.net/e5a4bd3e92f9c515b152683eecfcd967.jpg","caption":"Cinnamomum burmanni"}]}]}