{"totalResults":2,"page":1,"totalPages":1,"perPage":24,"cursor":"AoMIQA7Y+zg2MDBQb2FjZWFlSG9yZGV1bW1hcmludW0sVGF4b25fNzc4MTcx","message":"If you would like to download and use the POWO data in a conciencious way, please use our official library pykew [https://github.com/RBGKew/pykew].","results":[{"accepted":true,"author":"L.","kingdom":"Plantae","family":"Poaceae","name":"Hordeum vulgare","rank":"Species","snippet":" <b>Common Name</b>: winter barley","url":"/taxon/urn:lsid:ipni.org:names:405391-1","fqId":"urn:lsid:ipni.org:names:405391-1","images":[{"thumbnail":"//d2seqvvyy3b8p2.cloudfront.net/4d5b7754320aabe2eb0831a856f6af9a.jpg","fullsize":"//d2seqvvyy3b8p2.cloudfront.net/98face910738acb745ed7c70e79cc28b.jpg","caption":"Hordeum vulgare"},{"thumbnail":"//d2seqvvyy3b8p2.cloudfront.net/00733d21950ec2bf8dcb07cb31a3cc82.jpg","fullsize":"//d2seqvvyy3b8p2.cloudfront.net/b96f4c8b95faaabd500b1bdfcd8ab75e.jpg","caption":"Hordeum vulgare"},{"thumbnail":"//d2seqvvyy3b8p2.cloudfront.net/cdbf0c04ab2367cc82f316e7327e1108.jpg","fullsize":"//d2seqvvyy3b8p2.cloudfront.net/ff03af1caa36cd305fc3850d370677d5.jpg","caption":"Hordeum vulgare"}]},{"accepted":true,"author":"Huds.","kingdom":"Plantae","family":"Poaceae","name":"Hordeum marinum","rank":"Species","snippet":" <b>General</b>:   is an important wild relative of the major cereal grain  <em>Hordeum</em> <em>vulgare</em>","url":"/taxon/urn:lsid:ipni.org:names:30066468-2","fqId":"urn:lsid:ipni.org:names:30066468-2","images":[{"thumbnail":"//storage.googleapis.com/powop-assets/kew_profiles/KPPCONT_058862_thumbnail.jpg","fullsize":"//storage.googleapis.com/powop-assets/kew_profiles/KPPCONT_058862_fullsize.jpg","caption":"Hordeum marinum (sea barley)"},{"thumbnail":"//storage.googleapis.com/powop-assets/kew_profiles/KPPCONT_058854_thumbnail.jpg","fullsize":"//storage.googleapis.com/powop-assets/kew_profiles/KPPCONT_058854_fullsize.jpg","caption":"Hordeum marinum herbarium specimen"},{"thumbnail":"//d2seqvvyy3b8p2.cloudfront.net/b2fe8071422c0b9cb24ba0bf8ef4a1da.jpg","fullsize":"//d2seqvvyy3b8p2.cloudfront.net/51e1f45ec3da707dee0b2cae7487e443.jpg","caption":"A specimen from Kew's Herbarium"}]}]}