{"totalResults":3,"page":1,"totalPages":1,"perPage":24,"cursor":"AoMIQI0ZcTo2MDBGYWJhY2VhZU1lZGljYWdvZG9saWF0YSxUYXhvbl82ODAxMTM=","message":"If you would like to download and use the POWO data in a conciencious way, please use our official library pykew [https://github.com/RBGKew/pykew].","results":[{"accepted":false,"author":"Willd.","kingdom":"Plantae","family":"Fabaceae","name":"Medicago turbinata","rank":"Species","synonymOf":{"accepted":true,"author":"Carmign.","name":"Medicago doliata","url":"/taxon/urn:lsid:ipni.org:names:506159-1","fqId":"urn:lsid:ipni.org:names:506159-1"},"url":"/taxon/urn:lsid:ipni.org:names:3036131-4","fqId":"urn:lsid:ipni.org:names:3036131-4"},{"accepted":true,"author":"(L.) All.","kingdom":"Plantae","family":"Fabaceae","name":"Medicago turbinata","rank":"Species","url":"/taxon/urn:lsid:ipni.org:names:506480-1","fqId":"urn:lsid:ipni.org:names:506480-1","images":[{"thumbnail":"//d2seqvvyy3b8p2.cloudfront.net/49c1cd3825017eb96e25d64b0cde3a16.jpg","fullsize":"//d2seqvvyy3b8p2.cloudfront.net/ed991640f4ca4e25d5159ef7c004f3ea.jpg","caption":"Medicago turbinata"},{"thumbnail":"//d2seqvvyy3b8p2.cloudfront.net/3bb525445d8cbec3a200b317d68e3ce9.jpg","fullsize":"//d2seqvvyy3b8p2.cloudfront.net/6ae34c2242ac475b655f7b0db03f0bf7.jpg","caption":"Medicago turbinata"},{"thumbnail":"//d2seqvvyy3b8p2.cloudfront.net/ec24c403fbe39d4f21f4d796255794f8.jpg","fullsize":"//d2seqvvyy3b8p2.cloudfront.net/712908a9aebfffca88d3de679a7e52e6.jpg","caption":"A specimen from Kew's Herbarium"}]},{"accepted":true,"author":"Carmign.","kingdom":"Plantae","family":"Fabaceae","name":"Medicago doliata","rank":"Species","url":"/taxon/urn:lsid:ipni.org:names:506159-1","fqId":"urn:lsid:ipni.org:names:506159-1","images":[{"thumbnail":"//d2seqvvyy3b8p2.cloudfront.net/912fd577abf4fa87dd1cf12b8a48f5e4.jpg","fullsize":"//d2seqvvyy3b8p2.cloudfront.net/9ac2952c6c26c84c26bc12138f07393a.jpg","caption":"A specimen from Kew's Herbarium"},{"thumbnail":"//d2seqvvyy3b8p2.cloudfront.net/d7ea87d2f4e30136dd9b044dc566cd82.jpg","fullsize":"//d2seqvvyy3b8p2.cloudfront.net/046e19862410a78710fb8f6480bf0e95.jpg","caption":"A specimen from Kew's Herbarium"},{"thumbnail":"//d2seqvvyy3b8p2.cloudfront.net/aa84c896b1c9787e25cf8b6771a1fc21.jpg","fullsize":"//d2seqvvyy3b8p2.cloudfront.net/911005ea18f8e56cd7a480e6f5167d4e.jpg","caption":"A specimen from Kew's Herbarium"}]}]}