{"totalResults":2,"page":1,"totalPages":1,"perPage":24,"cursor":"AoMIQODmSTo2MDBQb2FjZWFlUGFuaWN1bWNvbG9yYXR1bSxUYXhvbl83NTgwMjU=","message":"If you would like to download and use the POWO data in a conciencious way, please use our official library pykew [https://github.com/RBGKew/pykew].","results":[{"accepted":false,"author":"Gooss.","kingdom":"Plantae","family":"Poaceae","name":"Panicum coloratum var. makarikariense","rank":"Variety","synonymOf":{"accepted":true,"author":"L.","name":"Panicum coloratum","url":"/taxon/urn:lsid:ipni.org:names:410989-1","fqId":"urn:lsid:ipni.org:names:410989-1"},"url":"/taxon/urn:lsid:ipni.org:names:126428-3","fqId":"urn:lsid:ipni.org:names:126428-3"},{"accepted":true,"author":"L.","kingdom":"Plantae","family":"Poaceae","name":"Panicum coloratum","rank":"Species","snippet":" <b>Common Name</b>: White buffalo grass","url":"/taxon/urn:lsid:ipni.org:names:410989-1","fqId":"urn:lsid:ipni.org:names:410989-1","images":[{"thumbnail":"//storage.googleapis.com/powop-assets/PPA/2001_2025/h2018a_thumbnail.jpg","fullsize":"//storage.googleapis.com/powop-assets/PPA/2001_2025/h2018a_fullsize.jpg","caption":"Panicum coloratum L."},{"thumbnail":"//storage.googleapis.com/powop-assets/PPA/2001_2025/h2018b_thumbnail.jpg","fullsize":"//storage.googleapis.com/powop-assets/PPA/2001_2025/h2018b_fullsize.jpg","caption":"Panicum coloratum L."},{"thumbnail":"//storage.googleapis.com/powop-assets/PPA/2001_2025/h2018c_thumbnail.jpg","fullsize":"//storage.googleapis.com/powop-assets/PPA/2001_2025/h2018c_fullsize.jpg","caption":"Panicum coloratum L."}]}]}